{"c:\\Users\\Chai\\Desktop\\11\\RMUC-2025\\Core\\Src\\can.c":"c:\\Users\\Chai\\Desktop\\11\\RMUC-2025\\MDK-ARM\\..\\MDK-ARM\\infantry\\.obj\\__\\Core\\Src\\can.o","c:\\Users\\Chai\\Desktop\\11\\RMUC-2025\\Core\\Src\\dma.c":"c:\\Users\\Chai\\Desktop\\11\\RMUC-2025\\MDK-ARM\\..\\MDK-ARM\\infantry\\.obj\\__\\Core\\Src\\dma.o","c:\\Users\\Chai\\Desktop\\11\\RMUC-2025\\Core\\Src\\gpio.c":"c:\\Users\\Chai\\Desktop\\11\\RMUC-2025\\MDK-ARM\\..\\MDK-ARM\\infantry\\.obj\\__\\Core\\Src\\gpio.o","c:\\Users\\Chai\\Desktop\\11\\RMUC-2025\\Core\\Src\\i2c.c":"c:\\Users\\Chai\\Desktop\\11\\RMUC-2025\\MDK-ARM\\..\\MDK-ARM\\infantry\\.obj\\__\\Core\\Src\\i2c.o","c:\\Users\\Chai\\Desktop\\11\\RMUC-2025\\Core\\Src\\main.c":"c:\\Users\\Chai\\Desktop\\11\\RMUC-2025\\MDK-ARM\\..\\MDK-ARM\\infantry\\.obj\\__\\Core\\Src\\main.o","c:\\Users\\Chai\\Desktop\\11\\RMUC-2025\\Core\\Src\\spi.c":"c:\\Users\\Chai\\Desktop\\11\\RMUC-2025\\MDK-ARM\\..\\MDK-ARM\\infantry\\.obj\\__\\Core\\Src\\spi.o","c:\\Users\\Chai\\Desktop\\11\\RMUC-2025\\Core\\Src\\stm32f4xx_hal_msp.c":"c:\\Users\\Chai\\Desktop\\11\\RMUC-2025\\MDK-ARM\\..\\MDK-ARM\\infantry\\.obj\\__\\Core\\Src\\stm32f4xx_hal_msp.o","c:\\Users\\Chai\\Desktop\\11\\RMUC-2025\\Core\\Src\\stm32f4xx_it.c":"c:\\Users\\Chai\\Desktop\\11\\RMUC-2025\\MDK-ARM\\..\\MDK-ARM\\infantry\\.obj\\__\\Core\\Src\\stm32f4xx_it.o","c:\\Users\\Chai\\Desktop\\11\\RMUC-2025\\Core\\Src\\system_stm32f4xx.c":"c:\\Users\\Chai\\Desktop\\11\\RMUC-2025\\MDK-ARM\\..\\MDK-ARM\\infantry\\.obj\\__\\Core\\Src\\system_stm32f4xx.o","c:\\Users\\Chai\\Desktop\\11\\RMUC-2025\\Core\\Src\\tim.c":"c:\\Users\\Chai\\Desktop\\11\\RMUC-2025\\MDK-ARM\\..\\MDK-ARM\\infantry\\.obj\\__\\Core\\Src\\tim.o","c:\\Users\\Chai\\Desktop\\11\\RMUC-2025\\Core\\Src\\usart.c":"c:\\Users\\Chai\\Desktop\\11\\RMUC-2025\\MDK-ARM\\..\\MDK-ARM\\infantry\\.obj\\__\\Core\\Src\\usart.o","c:\\Users\\Chai\\Desktop\\11\\RMUC-2025\\Drivers\\STM32F4xx_HAL_Driver\\Src\\stm32f4xx_hal.c":"c:\\Users\\Chai\\Desktop\\11\\RMUC-2025\\MDK-ARM\\..\\MDK-ARM\\infantry\\.obj\\__\\Drivers\\STM32F4xx_HAL_Driver\\Src\\stm32f4xx_hal.o","c:\\Users\\Chai\\Desktop\\11\\RMUC-2025\\Drivers\\STM32F4xx_HAL_Driver\\Src\\stm32f4xx_hal_can.c":"c:\\Users\\Chai\\Desktop\\11\\RMUC-2025\\MDK-ARM\\..\\MDK-ARM\\infantry\\.obj\\__\\Drivers\\STM32F4xx_HAL_Driver\\Src\\stm32f4xx_hal_can.o","c:\\Users\\Chai\\Desktop\\11\\RMUC-2025\\Drivers\\STM32F4xx_HAL_Driver\\Src\\stm32f4xx_hal_cortex.c":"c:\\Users\\Chai\\Desktop\\11\\RMUC-2025\\MDK-ARM\\..\\MDK-ARM\\infantry\\.obj\\__\\Drivers\\STM32F4xx_HAL_Driver\\Src\\stm32f4xx_hal_cortex.o","c:\\Users\\Chai\\Desktop\\11\\RMUC-2025\\Drivers\\STM32F4xx_HAL_Driver\\Src\\stm32f4xx_hal_dma.c":"c:\\Users\\Chai\\Desktop\\11\\RMUC-2025\\MDK-ARM\\..\\MDK-ARM\\infantry\\.obj\\__\\Drivers\\STM32F4xx_HAL_Driver\\Src\\stm32f4xx_hal_dma.o","c:\\Users\\Chai\\Desktop\\11\\RMUC-2025\\Drivers\\STM32F4xx_HAL_Driver\\Src\\stm32f4xx_hal_dma_ex.c":"c:\\Users\\Chai\\Desktop\\11\\RMUC-2025\\MDK-ARM\\..\\MDK-ARM\\infantry\\.obj\\__\\Drivers\\STM32F4xx_HAL_Driver\\Src\\stm32f4xx_hal_dma_ex.o","c:\\Users\\Chai\\Desktop\\11\\RMUC-2025\\Drivers\\STM32F4xx_HAL_Driver\\Src\\stm32f4xx_hal_exti.c":"c:\\Users\\Chai\\Desktop\\11\\RMUC-2025\\MDK-ARM\\..\\MDK-ARM\\infantry\\.obj\\__\\Drivers\\STM32F4xx_HAL_Driver\\Src\\stm32f4xx_hal_exti.o","c:\\Users\\Chai\\Desktop\\11\\RMUC-2025\\Drivers\\STM32F4xx_HAL_Driver\\Src\\stm32f4xx_hal_flash.c":"c:\\Users\\Chai\\Desktop\\11\\RMUC-2025\\MDK-ARM\\..\\MDK-ARM\\infantry\\.obj\\__\\Drivers\\STM32F4xx_HAL_Driver\\Src\\stm32f4xx_hal_flash.o","c:\\Users\\Chai\\Desktop\\11\\RMUC-2025\\Drivers\\STM32F4xx_HAL_Driver\\Src\\stm32f4xx_hal_flash_ex.c":"c:\\Users\\Chai\\Desktop\\11\\RMUC-2025\\MDK-ARM\\..\\MDK-ARM\\infantry\\.obj\\__\\Drivers\\STM32F4xx_HAL_Driver\\Src\\stm32f4xx_hal_flash_ex.o","c:\\Users\\Chai\\Desktop\\11\\RMUC-2025\\Drivers\\STM32F4xx_HAL_Driver\\Src\\stm32f4xx_hal_flash_ramfunc.c":"c:\\Users\\Chai\\Desktop\\11\\RMUC-2025\\MDK-ARM\\..\\MDK-ARM\\infantry\\.obj\\__\\Drivers\\STM32F4xx_HAL_Driver\\Src\\stm32f4xx_hal_flash_ramfunc.o","c:\\Users\\Chai\\Desktop\\11\\RMUC-2025\\Drivers\\STM32F4xx_HAL_Driver\\Src\\stm32f4xx_hal_gpio.c":"c:\\Users\\Chai\\Desktop\\11\\RMUC-2025\\MDK-ARM\\..\\MDK-ARM\\infantry\\.obj\\__\\Drivers\\STM32F4xx_HAL_Driver\\Src\\stm32f4xx_hal_gpio.o","c:\\Users\\Chai\\Desktop\\11\\RMUC-2025\\Drivers\\STM32F4xx_HAL_Driver\\Src\\stm32f4xx_hal_i2c.c":"c:\\Users\\Chai\\Desktop\\11\\RMUC-2025\\MDK-ARM\\..\\MDK-ARM\\infantry\\.obj\\__\\Drivers\\STM32F4xx_HAL_Driver\\Src\\stm32f4xx_hal_i2c.o","c:\\Users\\Chai\\Desktop\\11\\RMUC-2025\\Drivers\\STM32F4xx_HAL_Driver\\Src\\stm32f4xx_hal_i2c_ex.c":"c:\\Users\\Chai\\Desktop\\11\\RMUC-2025\\MDK-ARM\\..\\MDK-ARM\\infantry\\.obj\\__\\Drivers\\STM32F4xx_HAL_Driver\\Src\\stm32f4xx_hal_i2c_ex.o","c:\\Users\\Chai\\Desktop\\11\\RMUC-2025\\Drivers\\STM32F4xx_HAL_Driver\\Src\\stm32f4xx_hal_pcd.c":"c:\\Users\\Chai\\Desktop\\11\\RMUC-2025\\MDK-ARM\\..\\MDK-ARM\\infantry\\.obj\\__\\Drivers\\STM32F4xx_HAL_Driver\\Src\\stm32f4xx_hal_pcd.o","c:\\Users\\Chai\\Desktop\\11\\RMUC-2025\\Drivers\\STM32F4xx_HAL_Driver\\Src\\stm32f4xx_hal_pcd_ex.c":"c:\\Users\\Chai\\Desktop\\11\\RMUC-2025\\MDK-ARM\\..\\MDK-ARM\\infantry\\.obj\\__\\Drivers\\STM32F4xx_HAL_Driver\\Src\\stm32f4xx_hal_pcd_ex.o","c:\\Users\\Chai\\Desktop\\11\\RMUC-2025\\Drivers\\STM32F4xx_HAL_Driver\\Src\\stm32f4xx_hal_pwr.c":"c:\\Users\\Chai\\Desktop\\11\\RMUC-2025\\MDK-ARM\\..\\MDK-ARM\\infantry\\.obj\\__\\Drivers\\STM32F4xx_HAL_Driver\\Src\\stm32f4xx_hal_pwr.o","c:\\Users\\Chai\\Desktop\\11\\RMUC-2025\\Drivers\\STM32F4xx_HAL_Driver\\Src\\stm32f4xx_hal_pwr_ex.c":"c:\\Users\\Chai\\Desktop\\11\\RMUC-2025\\MDK-ARM\\..\\MDK-ARM\\infantry\\.obj\\__\\Drivers\\STM32F4xx_HAL_Driver\\Src\\stm32f4xx_hal_pwr_ex.o","c:\\Users\\Chai\\Desktop\\11\\RMUC-2025\\Drivers\\STM32F4xx_HAL_Driver\\Src\\stm32f4xx_hal_rcc.c":"c:\\Users\\Chai\\Desktop\\11\\RMUC-2025\\MDK-ARM\\..\\MDK-ARM\\infantry\\.obj\\__\\Drivers\\STM32F4xx_HAL_Driver\\Src\\stm32f4xx_hal_rcc.o","c:\\Users\\Chai\\Desktop\\11\\RMUC-2025\\Drivers\\STM32F4xx_HAL_Driver\\Src\\stm32f4xx_hal_rcc_ex.c":"c:\\Users\\Chai\\Desktop\\11\\RMUC-2025\\MDK-ARM\\..\\MDK-ARM\\infantry\\.obj\\__\\Drivers\\STM32F4xx_HAL_Driver\\Src\\stm32f4xx_hal_rcc_ex.o","c:\\Users\\Chai\\Desktop\\11\\RMUC-2025\\Drivers\\STM32F4xx_HAL_Driver\\Src\\stm32f4xx_hal_spi.c":"c:\\Users\\Chai\\Desktop\\11\\RMUC-2025\\MDK-ARM\\..\\MDK-ARM\\infantry\\.obj\\__\\Drivers\\STM32F4xx_HAL_Driver\\Src\\stm32f4xx_hal_spi.o","c:\\Users\\Chai\\Desktop\\11\\RMUC-2025\\Drivers\\STM32F4xx_HAL_Driver\\Src\\stm32f4xx_hal_tim.c":"c:\\Users\\Chai\\Desktop\\11\\RMUC-2025\\MDK-ARM\\..\\MDK-ARM\\infantry\\.obj\\__\\Drivers\\STM32F4xx_HAL_Driver\\Src\\stm32f4xx_hal_tim.o","c:\\Users\\Chai\\Desktop\\11\\RMUC-2025\\Drivers\\STM32F4xx_HAL_Driver\\Src\\stm32f4xx_hal_tim_ex.c":"c:\\Users\\Chai\\Desktop\\11\\RMUC-2025\\MDK-ARM\\..\\MDK-ARM\\infantry\\.obj\\__\\Drivers\\STM32F4xx_HAL_Driver\\Src\\stm32f4xx_hal_tim_ex.o","c:\\Users\\Chai\\Desktop\\11\\RMUC-2025\\Drivers\\STM32F4xx_HAL_Driver\\Src\\stm32f4xx_hal_uart.c":"c:\\Users\\Chai\\Desktop\\11\\RMUC-2025\\MDK-ARM\\..\\MDK-ARM\\infantry\\.obj\\__\\Drivers\\STM32F4xx_HAL_Driver\\Src\\stm32f4xx_hal_uart.o","c:\\Users\\Chai\\Desktop\\11\\RMUC-2025\\Drivers\\STM32F4xx_HAL_Driver\\Src\\stm32f4xx_ll_usb.c":"c:\\Users\\Chai\\Desktop\\11\\RMUC-2025\\MDK-ARM\\..\\MDK-ARM\\infantry\\.obj\\__\\Drivers\\STM32F4xx_HAL_Driver\\Src\\stm32f4xx_ll_usb.o","c:\\Users\\Chai\\Desktop\\11\\RMUC-2025\\Middlewares\\ST\\STM32_USB_Device_Library\\Class\\CDC\\Src\\usbd_cdc.c":"c:\\Users\\Chai\\Desktop\\11\\RMUC-2025\\MDK-ARM\\..\\MDK-ARM\\infantry\\.obj\\__\\Middlewares\\ST\\STM32_USB_Device_Library\\Class\\CDC\\Src\\usbd_cdc.o","c:\\Users\\Chai\\Desktop\\11\\RMUC-2025\\Middlewares\\ST\\STM32_USB_Device_Library\\Core\\Src\\usbd_core.c":"c:\\Users\\Chai\\Desktop\\11\\RMUC-2025\\MDK-ARM\\..\\MDK-ARM\\infantry\\.obj\\__\\Middlewares\\ST\\STM32_USB_Device_Library\\Core\\Src\\usbd_core.o","c:\\Users\\Chai\\Desktop\\11\\RMUC-2025\\Middlewares\\ST\\STM32_USB_Device_Library\\Core\\Src\\usbd_ctlreq.c":"c:\\Users\\Chai\\Desktop\\11\\RMUC-2025\\MDK-ARM\\..\\MDK-ARM\\infantry\\.obj\\__\\Middlewares\\ST\\STM32_USB_Device_Library\\Core\\Src\\usbd_ctlreq.o","c:\\Users\\Chai\\Desktop\\11\\RMUC-2025\\Middlewares\\ST\\STM32_USB_Device_Library\\Core\\Src\\usbd_ioreq.c":"c:\\Users\\Chai\\Desktop\\11\\RMUC-2025\\MDK-ARM\\..\\MDK-ARM\\infantry\\.obj\\__\\Middlewares\\ST\\STM32_USB_Device_Library\\Core\\Src\\usbd_ioreq.o","c:\\Users\\Chai\\Desktop\\11\\RMUC-2025\\USB_DEVICE\\App\\usb_device.c":"c:\\Users\\Chai\\Desktop\\11\\RMUC-2025\\MDK-ARM\\..\\MDK-ARM\\infantry\\.obj\\__\\USB_DEVICE\\App\\usb_device.o","c:\\Users\\Chai\\Desktop\\11\\RMUC-2025\\USB_DEVICE\\App\\usbd_cdc_if.c":"c:\\Users\\Chai\\Desktop\\11\\RMUC-2025\\MDK-ARM\\..\\MDK-ARM\\infantry\\.obj\\__\\USB_DEVICE\\App\\usbd_cdc_if.o","c:\\Users\\Chai\\Desktop\\11\\RMUC-2025\\USB_DEVICE\\App\\usbd_desc.c":"c:\\Users\\Chai\\Desktop\\11\\RMUC-2025\\MDK-ARM\\..\\MDK-ARM\\infantry\\.obj\\__\\USB_DEVICE\\App\\usbd_desc.o","c:\\Users\\Chai\\Desktop\\11\\RMUC-2025\\USB_DEVICE\\Target\\usbd_conf.c":"c:\\Users\\Chai\\Desktop\\11\\RMUC-2025\\MDK-ARM\\..\\MDK-ARM\\infantry\\.obj\\__\\USB_DEVICE\\Target\\usbd_conf.o","c:\\Users\\Chai\\Desktop\\11\\RMUC-2025\\User\\Chariot\\crt_booster.cpp":"c:\\Users\\Chai\\Desktop\\11\\RMUC-2025\\MDK-ARM\\..\\MDK-ARM\\infantry\\.obj\\__\\User\\Chariot\\crt_booster.o","c:\\Users\\Chai\\Desktop\\11\\RMUC-2025\\User\\Chariot\\crt_chassis.cpp":"c:\\Users\\Chai\\Desktop\\11\\RMUC-2025\\MDK-ARM\\..\\MDK-ARM\\infantry\\.obj\\__\\User\\Chariot\\crt_chassis.o","c:\\Users\\Chai\\Desktop\\11\\RMUC-2025\\User\\Chariot\\crt_gimbal.cpp":"c:\\Users\\Chai\\Desktop\\11\\RMUC-2025\\MDK-ARM\\..\\MDK-ARM\\infantry\\.obj\\__\\User\\Chariot\\crt_gimbal.o","c:\\Users\\Chai\\Desktop\\11\\RMUC-2025\\User\\Device\\CharSendTask.cpp":"c:\\Users\\Chai\\Desktop\\11\\RMUC-2025\\MDK-ARM\\..\\MDK-ARM\\infantry\\.obj\\__\\User\\Device\\CharSendTask.o","c:\\Users\\Chai\\Desktop\\11\\RMUC-2025\\User\\Device\\GraphicsSendTask.cpp":"c:\\Users\\Chai\\Desktop\\11\\RMUC-2025\\MDK-ARM\\..\\MDK-ARM\\infantry\\.obj\\__\\User\\Device\\GraphicsSendTask.o","c:\\Users\\Chai\\Desktop\\11\\RMUC-2025\\User\\Device\\dvc_GraphicsSendTask.cpp":"c:\\Users\\Chai\\Desktop\\11\\RMUC-2025\\MDK-ARM\\..\\MDK-ARM\\infantry\\.obj\\__\\User\\Device\\dvc_GraphicsSendTask.o","c:\\Users\\Chai\\Desktop\\11\\RMUC-2025\\User\\Device\\dvc_boardc_bmi088.cpp":"c:\\Users\\Chai\\Desktop\\11\\RMUC-2025\\MDK-ARM\\..\\MDK-ARM\\infantry\\.obj\\__\\User\\Device\\dvc_boardc_bmi088.o","c:\\Users\\Chai\\Desktop\\11\\RMUC-2025\\User\\Device\\dvc_boardc_ist8310.cpp":"c:\\Users\\Chai\\Desktop\\11\\RMUC-2025\\MDK-ARM\\..\\MDK-ARM\\infantry\\.obj\\__\\User\\Device\\dvc_boardc_ist8310.o","c:\\Users\\Chai\\Desktop\\11\\RMUC-2025\\User\\Device\\dvc_djimotor.cpp":"c:\\Users\\Chai\\Desktop\\11\\RMUC-2025\\MDK-ARM\\..\\MDK-ARM\\infantry\\.obj\\__\\User\\Device\\dvc_djimotor.o","c:\\Users\\Chai\\Desktop\\11\\RMUC-2025\\User\\Device\\dvc_dmmotor.cpp":"c:\\Users\\Chai\\Desktop\\11\\RMUC-2025\\MDK-ARM\\..\\MDK-ARM\\infantry\\.obj\\__\\User\\Device\\dvc_dmmotor.o","c:\\Users\\Chai\\Desktop\\11\\RMUC-2025\\User\\Device\\dvc_dr16.cpp":"c:\\Users\\Chai\\Desktop\\11\\RMUC-2025\\MDK-ARM\\..\\MDK-ARM\\infantry\\.obj\\__\\User\\Device\\dvc_dr16.o","c:\\Users\\Chai\\Desktop\\11\\RMUC-2025\\User\\Device\\dvc_dwt.cpp":"c:\\Users\\Chai\\Desktop\\11\\RMUC-2025\\MDK-ARM\\..\\MDK-ARM\\infantry\\.obj\\__\\User\\Device\\dvc_dwt.o","c:\\Users\\Chai\\Desktop\\11\\RMUC-2025\\User\\Device\\dvc_imu.cpp":"c:\\Users\\Chai\\Desktop\\11\\RMUC-2025\\MDK-ARM\\..\\MDK-ARM\\infantry\\.obj\\__\\User\\Device\\dvc_imu.o","c:\\Users\\Chai\\Desktop\\11\\RMUC-2025\\User\\Device\\dvc_lkmotor.cpp":"c:\\Users\\Chai\\Desktop\\11\\RMUC-2025\\MDK-ARM\\..\\MDK-ARM\\infantry\\.obj\\__\\User\\Device\\dvc_lkmotor.o","c:\\Users\\Chai\\Desktop\\11\\RMUC-2025\\User\\Device\\dvc_manifold.cpp":"c:\\Users\\Chai\\Desktop\\11\\RMUC-2025\\MDK-ARM\\..\\MDK-ARM\\infantry\\.obj\\__\\User\\Device\\dvc_manifold.o","c:\\Users\\Chai\\Desktop\\11\\RMUC-2025\\User\\Device\\dvc_minipc.cpp":"c:\\Users\\Chai\\Desktop\\11\\RMUC-2025\\MDK-ARM\\..\\MDK-ARM\\infantry\\.obj\\__\\User\\Device\\dvc_minipc.o","c:\\Users\\Chai\\Desktop\\11\\RMUC-2025\\User\\Device\\dvc_referee.cpp":"c:\\Users\\Chai\\Desktop\\11\\RMUC-2025\\MDK-ARM\\..\\MDK-ARM\\infantry\\.obj\\__\\User\\Device\\dvc_referee.o","c:\\Users\\Chai\\Desktop\\11\\RMUC-2025\\User\\Device\\dvc_sampler.cpp":"c:\\Users\\Chai\\Desktop\\11\\RMUC-2025\\MDK-ARM\\..\\MDK-ARM\\infantry\\.obj\\__\\User\\Device\\dvc_sampler.o","c:\\Users\\Chai\\Desktop\\11\\RMUC-2025\\User\\Device\\dvc_serialplot.cpp":"c:\\Users\\Chai\\Desktop\\11\\RMUC-2025\\MDK-ARM\\..\\MDK-ARM\\infantry\\.obj\\__\\User\\Device\\dvc_serialplot.o","c:\\Users\\Chai\\Desktop\\11\\RMUC-2025\\User\\Device\\dvc_servo.cpp":"c:\\Users\\Chai\\Desktop\\11\\RMUC-2025\\MDK-ARM\\..\\MDK-ARM\\infantry\\.obj\\__\\User\\Device\\dvc_servo.o","c:\\Users\\Chai\\Desktop\\11\\RMUC-2025\\User\\Device\\dvc_supercap.cpp":"c:\\Users\\Chai\\Desktop\\11\\RMUC-2025\\MDK-ARM\\..\\MDK-ARM\\infantry\\.obj\\__\\User\\Device\\dvc_supercap.o","c:\\Users\\Chai\\Desktop\\11\\RMUC-2025\\User\\Device\\dvc_witahrs.cpp":"c:\\Users\\Chai\\Desktop\\11\\RMUC-2025\\MDK-ARM\\..\\MDK-ARM\\infantry\\.obj\\__\\User\\Device\\dvc_witahrs.o","c:\\Users\\Chai\\Desktop\\11\\RMUC-2025\\User\\Interaction\\ita_chariot.cpp":"c:\\Users\\Chai\\Desktop\\11\\RMUC-2025\\MDK-ARM\\..\\MDK-ARM\\infantry\\.obj\\__\\User\\Interaction\\ita_chariot.o","c:\\Users\\Chai\\Desktop\\11\\RMUC-2025\\User\\Middleware\\Algorithm\\PID.cpp":"c:\\Users\\Chai\\Desktop\\11\\RMUC-2025\\MDK-ARM\\..\\MDK-ARM\\infantry\\.obj\\__\\User\\Middleware\\Algorithm\\PID.o","c:\\Users\\Chai\\Desktop\\11\\RMUC-2025\\User\\Middleware\\Algorithm\\QuaternionEKF.cpp":"c:\\Users\\Chai\\Desktop\\11\\RMUC-2025\\MDK-ARM\\..\\MDK-ARM\\infantry\\.obj\\__\\User\\Middleware\\Algorithm\\QuaternionEKF.o","c:\\Users\\Chai\\Desktop\\11\\RMUC-2025\\User\\Middleware\\Algorithm\\alg_MahonyAHRS.cpp":"c:\\Users\\Chai\\Desktop\\11\\RMUC-2025\\MDK-ARM\\..\\MDK-ARM\\infantry\\.obj\\__\\User\\Middleware\\Algorithm\\alg_MahonyAHRS.o","c:\\Users\\Chai\\Desktop\\11\\RMUC-2025\\User\\Middleware\\Algorithm\\alg_filter.cpp":"c:\\Users\\Chai\\Desktop\\11\\RMUC-2025\\MDK-ARM\\..\\MDK-ARM\\infantry\\.obj\\__\\User\\Middleware\\Algorithm\\alg_filter.o","c:\\Users\\Chai\\Desktop\\11\\RMUC-2025\\User\\Middleware\\Algorithm\\alg_fsm.cpp":"c:\\Users\\Chai\\Desktop\\11\\RMUC-2025\\MDK-ARM\\..\\MDK-ARM\\infantry\\.obj\\__\\User\\Middleware\\Algorithm\\alg_fsm.o","c:\\Users\\Chai\\Desktop\\11\\RMUC-2025\\User\\Middleware\\Algorithm\\alg_pid.cpp":"c:\\Users\\Chai\\Desktop\\11\\RMUC-2025\\MDK-ARM\\..\\MDK-ARM\\infantry\\.obj\\__\\User\\Middleware\\Algorithm\\alg_pid.o","c:\\Users\\Chai\\Desktop\\11\\RMUC-2025\\User\\Middleware\\Algorithm\\alg_power_limit.cpp":"c:\\Users\\Chai\\Desktop\\11\\RMUC-2025\\MDK-ARM\\..\\MDK-ARM\\infantry\\.obj\\__\\User\\Middleware\\Algorithm\\alg_power_limit.o","c:\\Users\\Chai\\Desktop\\11\\RMUC-2025\\User\\Middleware\\Algorithm\\alg_slope.cpp":"c:\\Users\\Chai\\Desktop\\11\\RMUC-2025\\MDK-ARM\\..\\MDK-ARM\\infantry\\.obj\\__\\User\\Middleware\\Algorithm\\alg_slope.o","c:\\Users\\Chai\\Desktop\\11\\RMUC-2025\\User\\Middleware\\Algorithm\\kalman_filter.cpp":"c:\\Users\\Chai\\Desktop\\11\\RMUC-2025\\MDK-ARM\\..\\MDK-ARM\\infantry\\.obj\\__\\User\\Middleware\\Algorithm\\kalman_filter.o","c:\\Users\\Chai\\Desktop\\11\\RMUC-2025\\User\\Middleware\\Algorithm\\user_lib.cpp":"c:\\Users\\Chai\\Desktop\\11\\RMUC-2025\\MDK-ARM\\..\\MDK-ARM\\infantry\\.obj\\__\\User\\Middleware\\Algorithm\\user_lib.o","c:\\Users\\Chai\\Desktop\\11\\RMUC-2025\\User\\Middleware\\Driver\\drv_adc.cpp":"c:\\Users\\Chai\\Desktop\\11\\RMUC-2025\\MDK-ARM\\..\\MDK-ARM\\infantry\\.obj\\__\\User\\Middleware\\Driver\\drv_adc.o","c:\\Users\\Chai\\Desktop\\11\\RMUC-2025\\User\\Middleware\\Driver\\drv_bsp-boarda.cpp":"c:\\Users\\Chai\\Desktop\\11\\RMUC-2025\\MDK-ARM\\..\\MDK-ARM\\infantry\\.obj\\__\\User\\Middleware\\Driver\\drv_bsp-boarda.o","c:\\Users\\Chai\\Desktop\\11\\RMUC-2025\\User\\Middleware\\Driver\\drv_can.cpp":"c:\\Users\\Chai\\Desktop\\11\\RMUC-2025\\MDK-ARM\\..\\MDK-ARM\\infantry\\.obj\\__\\User\\Middleware\\Driver\\drv_can.o","c:\\Users\\Chai\\Desktop\\11\\RMUC-2025\\User\\Middleware\\Driver\\drv_dwt.cpp":"c:\\Users\\Chai\\Desktop\\11\\RMUC-2025\\MDK-ARM\\..\\MDK-ARM\\infantry\\.obj\\__\\User\\Middleware\\Driver\\drv_dwt.o","c:\\Users\\Chai\\Desktop\\11\\RMUC-2025\\User\\Middleware\\Driver\\drv_i2c.cpp":"c:\\Users\\Chai\\Desktop\\11\\RMUC-2025\\MDK-ARM\\..\\MDK-ARM\\infantry\\.obj\\__\\User\\Middleware\\Driver\\drv_i2c.o","c:\\Users\\Chai\\Desktop\\11\\RMUC-2025\\User\\Middleware\\Driver\\drv_math.cpp":"c:\\Users\\Chai\\Desktop\\11\\RMUC-2025\\MDK-ARM\\..\\MDK-ARM\\infantry\\.obj\\__\\User\\Middleware\\Driver\\drv_math.o","c:\\Users\\Chai\\Desktop\\11\\RMUC-2025\\User\\Middleware\\Driver\\drv_spi.cpp":"c:\\Users\\Chai\\Desktop\\11\\RMUC-2025\\MDK-ARM\\..\\MDK-ARM\\infantry\\.obj\\__\\User\\Middleware\\Driver\\drv_spi.o","c:\\Users\\Chai\\Desktop\\11\\RMUC-2025\\User\\Middleware\\Driver\\drv_tim.cpp":"c:\\Users\\Chai\\Desktop\\11\\RMUC-2025\\MDK-ARM\\..\\MDK-ARM\\infantry\\.obj\\__\\User\\Middleware\\Driver\\drv_tim.o","c:\\Users\\Chai\\Desktop\\11\\RMUC-2025\\User\\Middleware\\Driver\\drv_uart.cpp":"c:\\Users\\Chai\\Desktop\\11\\RMUC-2025\\MDK-ARM\\..\\MDK-ARM\\infantry\\.obj\\__\\User\\Middleware\\Driver\\drv_uart.o","c:\\Users\\Chai\\Desktop\\11\\RMUC-2025\\User\\Middleware\\Driver\\drv_usb.cpp":"c:\\Users\\Chai\\Desktop\\11\\RMUC-2025\\MDK-ARM\\..\\MDK-ARM\\infantry\\.obj\\__\\User\\Middleware\\Driver\\drv_usb.o","c:\\Users\\Chai\\Desktop\\11\\RMUC-2025\\User\\Task\\tsk_config_and_callback.cpp":"c:\\Users\\Chai\\Desktop\\11\\RMUC-2025\\MDK-ARM\\..\\MDK-ARM\\infantry\\.obj\\__\\User\\Task\\tsk_config_and_callback.o","c:\\Users\\Chai\\Desktop\\11\\RMUC-2025\\MDK-ARM\\startup_stm32f407xx.s":"c:\\Users\\Chai\\Desktop\\11\\RMUC-2025\\MDK-ARM\\..\\MDK-ARM\\infantry\\.obj\\startup_stm32f407xx.o"}